pvcz/PVCZ-2019_GLDAS_NOAH025_3H_info.npz
pvcz/PVCZ-2019_ver0p2_world_PV_climate_stressors_and_zones.csv
pvcz/PVCZ-2019_ver0p2_world_PV_climate_stressors_and_zones.pkl
pvcz/PVCZ-2019_ver0p2_zones.npz
pvcz/PVCZ-2019_world_PV_climate_stressors_and_zones.csv
pvcz/PVCZ-2019_world_PV_climate_stressors_and_zones.pkl
pvcz/__init__.py
pvcz/main.py
pvcz/pvcz.py
pvcz-0.2.4.dist-info/LICENSE
pvcz-0.2.4.dist-info/METADATA
pvcz-0.2.4.dist-info/WHEEL
pvcz-0.2.4.dist-info/top_level.txt
pvcz-0.2.4.dist-info/RECORD
