Metadata-Version: 2.1
Name: pvcz
Version: 0.2.4
Summary: Photovoltaic climate zones and degradation stressors
Home-page: https://github.com/toddkarin/pvcz
Author: toddkarin
Author-email: pvtools.lbl@gmail.com
License: UNKNOWN
Platform: UNKNOWN
Classifier: Programming Language :: Python :: 3
Classifier: License :: OSI Approved :: MIT License
Classifier: Operating System :: OS Independent
Requires-Dist: numpy
Requires-Dist: pandas
